zhuque_graph/__init__.py
zhuque_graph/nn/pytorch/model/LinkPredictionWgGNNModel.py
zhuque_graph/nn/pytorch/model/NodeClassificationWgGNNModel.py
zhuque-1.0.2.dist-info/METADATA
zhuque-1.0.2.dist-info/WHEEL
zhuque-1.0.2.dist-info/top_level.txt
zhuque-1.0.2.dist-info/RECORD
