Metadata-Version: 2.1
Name: zhuque
Version: 1.0.2
Summary: zhuque graph platform
Home-page: UNKNOWN
Author: zhuque
Author-email: zhuquezhitu@zhejianglab.com
License: GPL 3.0
Platform: UNKNOWN
